discordSplash/__init__.py
discordSplash/audit_log.py
discordSplash/channel.py
discordSplash/emoji.py
discordSplash/guild.py
discordSplash/invite.py
discordSplash/member.py
discordSplash/opcodes.py
discordSplash/template.py
discordSplash/webhook.py
discordSplash/resources/__init__.py
discordSplash/resources/opcodes.py
discordSplash-0.6a2.dist-info/LICENSE
discordSplash-0.6a2.dist-info/METADATA
discordSplash-0.6a2.dist-info/WHEEL
discordSplash-0.6a2.dist-info/top_level.txt
discordSplash-0.6a2.dist-info/RECORD
