Metadata-Version: 2.1
Name: discordSplash
Version: 0.6a2
Summary: An API wrapper for Discord's slash commands. Written in Python.
Home-page: https://github.com/Mineinjava/discord-splash
Author: Mineinjava
Author-email: Mineinjava@gmail.com
License: UNKNOWN
Platform: UNKNOWN
Classifier: Programming Language :: Python :: 3
Classifier: Operating System :: OS Independent
Requires-Python: >=3.7
